README.md
setup.py
forecastability/__init__.py
forecastability/forecastability.py
forecastability/period_detect.py
forecastability/util.py
forecastability.egg-info/PKG-INFO
forecastability.egg-info/SOURCES.txt
forecastability.egg-info/dependency_links.txt
forecastability.egg-info/top_level.txt