Metadata-Version: 2.1
Name: forecastability
Version: 0.0.6
Summary: forecastability analysis
Home-page: https://github.com/jingw2/solver/tree/master/forecastability
Author: Jing Wang
Author-email: jingw2@foxmail.com
License: MIT
Platform: UNKNOWN
Requires-Python: >=3.6
